kivy_plot/__init__.py
kivy_plot/histlayout.py
kivy_plot/linelayout.py
kivy_plot/pielayout.py
kivy_plot-0.0.4.dist-info/LICENSE
kivy_plot-0.0.4.dist-info/METADATA
kivy_plot-0.0.4.dist-info/WHEEL
kivy_plot-0.0.4.dist-info/top_level.txt
kivy_plot-0.0.4.dist-info/RECORD
