Metadata-Version: 2.1
Name: kivy_plot
Version: 0.0.4
Summary: 基于kivy绘画库
Author-email: iewv <3224218406@qq.com>
Project-URL: Homepage, https://github.com/pypa/sampleproject
Project-URL: Issues, https://github.com/pypa/sampleproject/issues
Classifier: Programming Language :: Python :: 3
Classifier: License :: OSI Approved :: MIT License
Classifier: Operating System :: OS Independent
Requires-Python: >=3.8
License-File: LICENSE
